{"attachments":["f-ra_001.tif"],"text":"--\n\n\n----- Препратено писмо от tbl_ood@mail.bg -----\n\nДата: 13.10.2021 в 10:36\nПодател: rr_oficce rr_oficce (rr_oficce@abv.bg)\nОтносно: декларация от Деница\nПолучател: tbl_ood@mail.bg \n\n\n\n-------------------------------------\nИскаш ли сайт на супер цена? Вече можеш да го направиш сам бързо и лесно.\nТествай безплатно Сайт билдър от СуперХостинг.БГ и вземи 65% отстъпка на избран от теб план.\n<http://ads.mail.bg/delivery/ck.php?oaparams=2__bannerid=4422__zoneid=35__OXLCA=1__cb=a841aeac32__oadest=https%3A%2F%2Fwww.superhosting.bg%2Fsite-builder.php%3Futm_source%3Dmbg%26utm_medium%3Dcpm%26utm_content%3Dmail_footer_3%26utm_campaign%3Dsb-pr21>","subject":"FWD: декларация от Деница","date":"2021-10-13T13:05:00.000Z","to":[{"address":"milena_stoychova@abv.bg","name":""}],"attachmentsData":[false]}