{"attachments":[],"text":"Благодаря!\n\nХубав ден! <http://mail.bg/images/html_smiley_04.gif> \n\n\n\n--\n\n\n----- Цитат от Rumen Vasilev (rvasilev@bdzcargo.bg), на 08.07.2021 в 11:05 -----\n\n\tГаранцията по договора е усвоена на база на това писмо..\n\n\tПоздрави,\n\t\n\t\n\t---------- Forwarded message ---------\n\tОт: Accounting Dep. <tp_account@bdzcargo.bg <mailto:tp_account@bdzcargo.bg> >\n\tDate: чт, 8.07.2021 г. в 12:01 ч.\n\tSubject: Fwd: Scan from YSoft SafeQ\n\tTo: Rumen Vasilev <rvasilev@bdzcargo.bg <mailto:rvasilev@bdzcargo.bg> >\n\t\n\n\n\n\n\t---------- Forwarded message ---------\n\tОт: <printer@bdzcargo.bg <mailto:printer@bdzcargo.bg> >\n\tDate: чт, 8.07.2021 г. в 12:00 ч.\n\tSubject: Scan from YSoft SafeQ\n\tTo: <tp_account@bdzcargo.bg <mailto:tp_account@bdzcargo.bg> >\n\t\n\n\n\tScan for the user Отдел Счетоводство (tp_account) from the device SOFCU03P05A3B\n\n\n\t-- \n\t\n\tС уважение,\n\t\n\t\n\tотдел \"Счетоводство\"\n\t\"БДЖ - Товарни превози\" ЕООД\n\t\n\n\n\t-- \n\t\n\n\tРумен Василев\n\n\tРъководител отдел \"Финансов мениджмънт\"\n\n\t\"БДЖ Товарни превози\" ЕООД\n\n\tтел. +359884 992 405\n\n\t <https://docs.google.com/uc?export=download&id=1sIqHGYSQHkqaU3DB4eLW2ZkkvGOFNcPa&revid=0B_HtgUi4nbI_Mk82SEJ5ekNZT1crSmV5RUVpL0ZnMXcrVytBPQ> \n\t\n\n\n\n-------------------------------------\nФен си на сладкарството и го развиваш като хоби? А имаш ли всичко необходимо за перфектния десерт? \nНаправи го неустоим, като подсилиш неговия вкус и аромат.\nВ boichka.bg те очаква богато разнообразие от сладкарски оцветители и аромати с премиум качество.\nВиж пълната гама със сладкарски продукти и развихри фантазията си в кухнята.\n<http://ads.mail.bg/delivery/ck.php?oaparams=2__bannerid=4365__zoneid=35__OXLCA=1__cb=43effb0a93__oadest=https%3A%2F%2Fboichka.bg%2F>","subject":"RE: Fwd: Scan from YSoft SafeQ","date":"2021-07-08T12:29:03.000Z","to":[{"address":"","name":"Rumen Vasilev"}],"attachmentsData":[]}