{"attachments":["F-ra_356_Tibiel.pdf"],"subject":"Fwd: Ф-ри м.01.2023","date":"2023-02-08T17:02:40.000Z","to":[{"address":"tbl_ood@mail.bg","name":""}],"attachmentsData":["Получател\nДоставчик\nТИБИЕЛ ЕООД\nВАНЯ КОЙЧЕВА МИЛЧЕВА\nАдрес\nАдрес\nгр. Перник, пл. Свети Иван Рилски №1\nжк.Дружба 281 вх. Б ет. 1 ап.2\nВИК/ЕГН:\n106588084\nЕИК/ЕГН:\n179548137\nИН по ДДС\nBG106588084\nИН по ДДС\nBG179548137\nФАКТУРА\nОригинал\nНомер\n0000000356\nДата\n31.01.2023\nNo\nНаименование на стоката/услугата\nМярка\nКолич.\nЕд. Цена\nЕд.Цена\nEUR\nBGN\nСтойност\nАбонементна такса по договор за абонаментно правно\nобслужване за месец Януари 2023 г.п\nбр\n1\n1 000.00\n1 000.00\nв Основание за неначисляване на ДДС.\nСтойност на сделката (BGN):\n1 000.00\nв Основание за нулевая ставка на ДДС.\nДанъчна основа (BGN):\n1 000.00\nДата на данъчного събитие/Дата на\n31.01.2023\nСтавка на ДДС.\nплащането:\n20%\nДДС (BGN):\n200.00\nСума за плащане (словом): хиляда и двеста лева\nСума за плащане (BGN):\n1 200.00\nСъCTaBuTeA:\nВаня Койчева Милчева\nРайфайзенбанк България ЕАД\nБанка\nВид на плащане:\nПо банков път\nBIC\nRZBBBGSF\n(имя, фамилия, подпис, печат)\nIBAN\nBG07RZBB91551004869118"]}