{"attachments":["872_БОБОВ_ДОЛ_НАЕМ.pdf"],"text":"From: Accounting <accounting@hpubg.com> \nSent: Tuesday, July 16, 2024 10:54 AM\nTo: d_bojchev@tecbd.com\nSubject: НАЕМ","subject":"FW: НАЕМ","date":"2024-07-16T11:16:26.000Z","to":[{"address":"tbl_ood@mail.bg","name":""}],"attachmentsData":["Получател:\nДоставчик:\nТЕЦ БОБОВ ДОЛ АД\nХИДРО ПАУЪР ЮТИЛИТИС ЕООД\nгр./с./ с. Големо село\nФАКТУРА\nгр./с./ гр. София\nАдрес:\nNo 0000000872\nАдрес: ул. Кукуш №1\nИдентиф. № ДДС: BG109513731\nДата: 16.07.2024\nИдентиф. № ДДС: BG205243702\nИдентиф. No: 109513731\nИдентиф. No: 205243702\nБанка:\nБанка: ИНВЕСТБАНК АД\nКод:\nОРИГИНАЛ\nКод: IORTBGSF\nСметка:\nСметка: BG61IORT80481093724900\nШифър\nНаименование\nМярка\nКол-во\nЕд.цена\nТО Ед.цена-ТО\nСтойност\n030001\nНАЕМ ТЕЛЕСКОПИЧЕН ТОВАРАЧ ВОВСАТ\nБР\n2,000\n2620.000\n2620.000\n5240.00\n35.70, СЪГЛАСНО ДОГОВОР ЗА М.07/2024\nСловом: шест хиляди двеста осемдесет и осем лв.\nДанъчна основа:\n5240.00\nДДС: 20 %\n1048.00\nСума за плащане в лева:\n6288.00\nДата на възникване на даньчното събитие: 16.07.2024\nПлащане: Платежно нареждане\nСтоката получена от:\nДата на плащане:\nПолучател:\nСъставил:\nИдентификационен шифьр:\nСогласно чл.7, ал.1 от Закона за счетоводството печатьт не е задължителен реквизит на првичните счетоводни документи.\nСъздал програмния продукт : \"СОФТСИСТЕМС\"ООД - гр. Стара Загора, ул. \"Ген. Столетов\" №69, тел. (042) 62 20 43\nСтр. 1"]}