{"attachments":["9200--0058052-2025-3800058129.pdf"],"text":"С най-добри пожелания,                                                   \nЕлена Ковачки\nАдминистрация и Бек Офис                                             \nМоб: +359 893 659 834                                                                                                                                                \nwww.tibiel.com     \nТИБИЕЛ ЕООД    \n\n                                                              \n\n-----Original Message-----\nFrom: Zapantioti, Vasileia-Paraskevi <V.Zapantioti@athexgroup.gr> \nSent: Friday, January 3, 2025 5:15 PM\nTo: Backoffice <Backoffice@tibiel.com>; invoices-enexclear <invoices-enexclear@athexgroup.gr>\nSubject: 9200 ELECTRONIC INVOICE SENDING - [CONFIDENTIAL]\n\n[ CLASSIFICATIOΝ: CONFIDENTIAL ]\n\nWe send you the invoice of company ΕnEx CLEARING HOUSE  SA with number 0058052 of date 03.01.2025\n\n\n\nSincerely yours\n\n[End of Classified Mail]","subject":"FW: 9200 ELECTRONIC INVOICE SENDING - [CONFIDENTIAL]","date":"2025-01-06T08:52:18.000Z","to":[{"address":"tbl_ood@mail.bg","name":""},{"address":"","name":"ТИБИЕЛ ЕООД"}],"attachmentsData":["EnEx CLEARING HOUSE SINGLE MEMBER S.A.\nenex\nATHINON AVENUE 110 10442 ATHENS GREECE\nTEL:+302103366400 - FAX:+302103366875\nTAX ID: EL801057201 - (GEMI): 148043601000\nclear\nPAGE 1 FROM 1\nSELF BILLING - INVOICE\nVENDOR DETAILS\nDOCUMENT DETAILS\nDEBTOR CODE: 5001000567\nNAME: TIBIEL Ltd\nSERIES/NUMBER: X 0058052\nADDRESS: 29 Knyaz Al. Dondukov boulevard\nBILLING DATE: 03.01.2025\nCITY: Sofia Bulgaria P.C .: 1000\nSAP DOCUMENT NUMBER: 3800058129\nTEL:\nCURRENCY: EUR\nVAT Reg. Num: BG106588084\nPAYMENT TERMS: ALREADY PAID\nCLEARING ACCOUNT: EBE\nNAME OF CLEARING MEMBER:\nTPATIEZA EUROBANK AE\nCLEARING DATE 03.01.2025\nITEM\nDESCRIPTION\nQUANTITY\nNET\nVAT%\nCODE\nMWH\nVALUE\n900001354\nSells on HEnEX GAS Trading Platform\n100,000\n4.600,00\nDelivery Date: 03/01/2025\nVAT\nNET\nVAT\nTOTAL TO\nVALUE\nVALUE\nBE PAID\n4.600,00\n4.600,00\nTOTAL VALUE in EUR:\n4.600,00\nAccording to Ar.44 of the EU VAT Directive, VAT is due by the recipient\nof the service. Also, Ar.38 is applied where applicable.\nThe current invoice is issued according to the provisions of the \"Clearing Rulebook For\nTransactions on HEnEX's Natural Gas Trading Platform\" and the corresponding Decisions of\nEnExClear.\nMARK ID: 400008192390260 UID: E587AFD941654D2EC7A461A7292294ECB65215D2"]}