{"attachments":["ф-ра_DHL_май.pdf","ф-ра_ЕКОС_17_22_05_2023.pdf"],"text":"Моля фактурите да се заявят за плащане","subject":"за заявка за плащане","date":"2023-05-23T16:02:54.000Z","to":[{"address":"","name":"ТИБИЕЛ ЕООД"},{"address":"tbl_ood@mail.bg","name":""}],"attachmentsData":["DHL Express\nDHL=\n** ФАКТУРА* ОРИГИНАЛ\nТИБИЕЛ ЕООД\nФактура номер:\n2000197503\nДИМИТЪР ЙОРДАНОВ ИВАНОВ\nDHL Референция:\nSOF0901300\nПЛОЩАД СВЕТИ ИВАН РИЛСКИ NO 1\nКлиентски номер:\n2300 ПЕРНИК\nДДС номер:\n316289379\nBG106588084\nДата на фактура:\nБрой страници:\n22/05/2023\n1 от 2\nЗа запитване относно фактури\nUIC: 106588084\nТелефон:\nИмейл:\n+359 700 17 700 (4)\nSoffinqueries@dhl.com\nВид услуга\nБрой\nОбщо\nБрой\nЦена на\nОбщо\nДДС Обща сума\nпратки\nтегло парчета\nтранспорт допълнител-\n(с ДДС)\nни такси\nEXPRESS ENVELOPE\n2\n0.50\n2\n113,08\n32,21\n29,08\n174,35\nОбщо\n2\n0,50\n2\n113,08\n32,21\n29.06\n174,35\nДопълнителни такси\nОбщо\nFUEL SURCHARGE\n32.0\nEMERGENCY SITUATION\n0,20\nОбщо дополнителни такси\n32,21\nддс\nОбща\nКод\nОписане на ДДС код\nСтавка\nОблагаема сума\nДДС\nОбщо ДДС\nA\n20% ДДС\n20,00%\n145,29\n29.06\n29,06\nОбща сума (без ДДС)\nДД\nОбще (с ДДС)\nСрок за плащане: 29/05/2023\nОбща сума (BGN)\n145,29\n29,06\n174,35\nДатата на данъчно събитие е датата на пратката.\nНастоящая документ е подписан с универсален електронен подпис.\nЗа всички фактури, неплатени на падежа, DHL си запазва правото да начисли 2% лихва от дължимата сума и да спре услугите на кредит.\nВсеки спор по настоящата фактура трябва да буде отправен към DHL в рамките на 7 дни от датата на фактурата.\nДи Ейч Ел Експрес България ЕООД\nwww.dhl.bg\nBank Name: Unicredit Bulbank AD\nул. Мария Атанасова 5\nИмейл: soffinqueries@dhl.com\nBIC: UNCR BGSF\n1540 София, България\nTen: +359 700 17 700 (4)\nIBAN BGN: BG94 UNCR 7000 1523 5637 98\nЕИК: 121333475\nIBAN EUR: BG40 UNCR 7000 1523 5638 00\nИН по ДДС: BG121333475\nПредставитель на получателя\nА. Иванова\nФактура номер:\n2000197503\n** ФАКТУРА ** ОРИГИНАЛ\nКлиентски номер:\n316289379\nДата на фактура:\n22/05/2023\nБрой страници:\n2 01 2\nAWB\nРеференция на\nPara Ha\nИзпращач\nДестинация / Получателя\nВид\nTerno 8\n6poR\nLieHa Ha\nДополнителни\nДопъяни-\nДДС / код\nManpaujava\nnparka\nycnyra\nKg\nTpaHC-\nтакси - описание\nTERHI TAKCH\ncyMa (c\nnopr\nyMa\nДО\n6981976035\n15/05/2023 SOF, SOFA\nBUH, BUCHAREST\nEXPRESS\n0,20 V\n1\n56,54\n21,31 A\nTIBIEL FOOD\nALMAIORDACHE\nENVELOPE\nFUEL SURCHARGE\n67,85\n16,00\n3,20 A\nAlice Iordache\n19,20\nDIMITAR IVANOV\nBUL DONDUKOV 29\nEMERGENCY SITUATION\n0.08\n002 A\n0,10\nPLOIESTI, NR. LA CLADIREA C,ET.I\nBULGARIA BULGARIA\nROVAN'A $1 S1 ROMANIA\nBG-1000, SOFIA\nRO-010415, BUCHAREST\nBulgaria\nRomania\n87,15\n3291000156\n18/05/2023 SOF, SOFIA\nATH, ATHENS\nTALLON COMMODITIES LTD\nEXPRESS\n56,54\nTIBTEL FOOD\n0,30 ª\n11,31 A\nENVELOPE\n67,85\n3.20 A\nDIMITAR IVANOV\nMargarita Alban dou:\nFUEL SURCHARGE\n16,01\n19,27\nEMERGENCY SITUATION\nBUL DONDUKOV 29\n342 KIFFISIAS AVENUE\n0.12\n0.0Z A\n0,14\nBULGARIA BULGARIA\nATHENS BG BG ATHENS\nBG-1000, SOFIA\nGR-154 51, NEO PSYCHIKO\nBulgaria\nATHENS\n87,20\nOGuia cyma no yotyre - EXPRESS ENVELOPE\n2\n113,08\n32,21\n29,06\n174,35\nOGuo: BGN:\n3.50\n113,08\n32,21\n29,06\n174,35\nA a Poarno TerRO no RAHHA HA ErOPHIA: V = DOOMHO TOTDO, NIO OHHH HỌ KNECHTA B = DHL Peanro Terno W = Dril oSevio ferro M = Kovrinekcho","Фактура\nОригинал\nНомер:\n0300000310\nДата:\n22.05.2023\nПолучатель\nТИБИЕЛ ЕООД\nДоставчик\nЕКОС 17 ООД\nДДС №\nBG 106588084\nДДС №\nBG201470204\nИдент. №\n106588084\nИдент. №\n201470204\nГрад\nСофия 1000\nГрад\nСофия\nАдрес\nбул. „Княз Александар Дондуков\" №\nАдрес\n29, офис 1\nж.к. Хаджи Димитър, ул. Резбарска 24\nМОЛ\nДимитър Иванов\nМОЛ\nКрасимир Бонев\nТелефон\nТелефон\n№\nКод\nНаименование на стоката/услугата\nМярка\nКоличество\nЦена\nСума\n1\n138\nДОСТАВКА НА ПРИРОДЕН ГАЗ съгласно\nMWh\n75.0000\n60.5000\n4 537.50\nсделка номер 125017 на БГХ за\n22.05.2023 г.\nДанъчна основа 9%\n4 537.50\nДДС 9%\n408.38\nСума за плащане:\n4 945.88\nСловом: Четири хиляди деветстотин четиридесет и пет лв. и 88 ст.\nДата на данъчно събитие:\n22.05.2023\nПлащане:\nПо сметка\nОснование на сделката:\nIBAN:\nBG21RZBB91551009809852-BGN\nОписание на сделката:\nБанка:\nКей Би Си Банк България ЕАД\nМясто на сделката\nБанков код:\nRZBBBGSF\nПолучил: Димитър Иванов\nСъставил:\nКрасимир Бонев\nфактурата:\nСогласно чл: 6, ап. 1 от Закона за счетоводството, чп. 114 от З/ДС и чп. 78 от ППЗДДС печатьт и подлисьт не са задолжителни реквизити вља\nПредставитель на получателя\nА. Иванова\nQR код за автоматично разплащане и осчетоводяване\nMicroinvest Invoice Pro\nwww.microinvest.net\nтел.0700 44 700"]}