{"attachments":["2-2846.pdf"],"text":"--\n\n\n-------------------------------------\nВреме е да обновите летния си гардероб?\nНаправете го с keipi.bg. Ние знаем тайната на истински добрата визия, подплaтена с елегантност и стил. \nА дизайнът на нашите модели носи почерка на модерната жена, излъчваща увереност и класа.\nВижте летните ни предложения и се оставете на изкушението да бъдете най-добрата версия на себе си.\n<http://ads.mail.bg/delivery/ck.php?oaparams=2__bannerid=4349__zoneid=35__OXLCA=1__cb=4fd35efbed__oadest=https%3A%2F%2Fkeipi.bg%2F>","subject":"f-ra naem","date":"2021-05-20T13:36:34.000Z","to":[{"address":"","name":"петя добрева"}],"attachmentsData":["ТИБИЕЛ ЕООД\nФАКТУРА ОРИГИНАЛ\n2000002846 / 03.05.2021\nПОЛУЧАТЕЛЯ : МИНА БЕЛИ БРЕГ АД\nДОСТАВЧИК : ТИБИЕЛ БООД\nВИН\n: 122016549\nБИН\n: 106588084\nДДС №\n: BG122016549\nДДС №\n: BG106588084\nАДРЕС\n: С.ГАБЕР - СОФИЙСКА ОБЛ., ПК 2215\nАДРЕС\n: гр. Перник площад Иван Рилски 1\nОВЕКТ\nOBEKT\n: ТИВИЕЛ ЕООД\nBAHKA\n: Уникредит Булбанк АД\nCMETKA\n: BG66UNCR70001521765243 / UNCRBGSF\nBAHKA\n: ЮРОБАНК ВЪЛГАРИЯ ДД\nCMETKA\n: BG50BPBI79251061849901 / BPBIBGSF\nNo|\nКод\n1\nАртикул\n|Мярка | Количество| Единична Цена |\nСтойност |\n11\nO|HAEM BATEP EH 631 - MEE\nBP\n1.000|\n200.000001\n200.00|\n21\n0|НАЕМ БУЛЬДОЗЕР SD 22 SHANTUI С ПРАВО ГРЕЕЛО - МББ\n| BP\n1.000|\n500.00000|\n500.00|\n31\nO | HAEM MAS 500 -MEE\nEP\n1.000|\n50.00000|\n50.00\nДАНЂИНА ОСНОВА\n750.00\nCTABKA HA ZANIKA : 20.00%\nPASMEP HA JAHLKA\n150.00\nBCMYKO :\n900.00\nСловом обща сума: /Деветстотин лева/\nПлащане : По Сметка\nДата на данъчно събитие: 03.05.2021\nПРИЕЛ :\nСЪСТАВИЛ :\n11\n/ЖАНА ГЪЛЬВОВА/\nЗабележка:\nIntegra Corporate System, Designeg By SmartPro Ltd., Varna, tel .: 052/505224\nPage 1 of 1"]}