{"attachments":["1806.pdf","1815.pdf"],"subject":"фактури м.06.2022","date":"2022-07-06T11:21:13.000Z","to":[{"address":"tbl_ood@mail.bg","name":""}],"attachmentsData":["Получатель\nПЕН Бобов дол Е000\n\"ГЛОБАЛ ЕКСПРЕС, ЕООД\nс. Голено село\nгр. София, инд. зона \"Орион\"\nАдрес\nул. 3020, № 34, ет. 5\nИДЕНТИФИКАЦИОНЕН № по ЗДДС:\n30х 109513831\nФАКТУРА\nИдентификационен №: 200657927\nИдентификационен № ЈЕГН/\n№ 0000001806\nИдентиф. № по ЗДДС: BG200657927\n10951373\nДата на\nиздавана\n30.06.2022г.\nNe\nнаименование на стоката / услугата\nмярка\nколичество\nединична\nцена\nстойност\n1\nнаем согласно договор за 1. 06.2022\n-\n2\nХюндай Туксон с рег. №° СВ4 562СХ\n833;33\n3\n-\n4\n5\n6\nОРШИН\n-\n7\n8\nСума за\nхильда лева\nДанъчна\n833,33\nоснова\nплащане\nДанъчна\nРазмер на\nс думи\nставка\nданька\n166167\nСума за\nплащане\nЛОДО РФ\nОснование за неначисляване.\nначин на плащане\nв брой\n15 с пл. нареждане\nна ДДС /Нулева ставка/\nсметка IBAN: 562REINV9150161591557Л\nДДС е изискуем от:\nполучателя\nпридобиващия\nДАТА на плащане:\n30.06.2022г.\nпри банка: ПИБ РД\nВІС код: 1\nn: FINVBGSF\nДАТА на дан. събитие:\nТо пола\nА. Гаврилова\nот:\nСъставил\n(име, фамилия, подпис)\nnevar \"Xanen 23\" EOOn, Ten .: 02 / 93 111 04","Получатель\nПиви Ел ЕООД\n\"ГЛОБАЛ ЕКСПРЕС, ЕООД\nгр. Перник, пл. СВ. Иван Рилски №2Л\nгр. София, инд. зона \"Орион\"\nАдрес\nул. 3020, № 34, ет. 5\nИДЕНТИФИКАЦИОНЕН № по ЗДДС:\n86106588084\nФАКТУРА\nИдентификационен №: 200657927\nИдентификационен № ЈЕГН/\nNo 0000001815\nИдентиф. № по ЗДДС: BG200657927\n106588084\nДата на\nиздаване\n№ 30.06.2022 г.\nNo\nнаименование на стоката / услугата\nмярка\nколичество\nединична\nцена\nстойност\n1\nкурперски и транспортии услуги\n3520,40\n2 по договор и опис\n3\n-\n4\n5\n-\n6\nОРИГИНАЛ\n7\n-\n8\nСума за\nчетири хихади двеста двадесет\nДанъчна\n3520,40\nоснова\nплащане\nДанъчна 1%\nставка\nPa3Mep Ha\nс думи\nи четири АВ. / 0,48 ст) 0\nданька\n704/08\nСума за\nплащане\n4224,48\nОснование за неначисляване\nначин на плащане\nв брой\nс пл. нареждане\nна ДДС /Нулева ставка\nСметка IBAN: 3621FINV9450101591557Л\nДДС е изискуем от:\nполучателя\nпридобиващия\nДАТА на плащане:\nДАТА на дан. събитие:\n30.06.2022г.\nпри банка: _\nПИБ АД\nПО ПОША\nА. Гаврилова\nВІС код: FINVBGSR\nот:\n(име, фамилия, подпис)\nСъставил:\n(ме, фамилия, подпис)\nПечат \"Халви 23\" ЕООД, тел .: 02 / 93 111 04"]}