{"attachments":["Продажби_ФАКТУРА_03_1000173944.pdf"],"text":"„Еуратек Финанс ”АД гр.София\n\n                                                                                                \n\n \n\n \n\nЗдравейте,\n\nСлед присъединяване на Райфайзенбанк АД към ОББ АД, Ви уведомяваме, че има промяна на банковите сметки на дружеството.\n\nТова е отразено в месечните фактури,които изпращаме за лизинговите вноски.\n\n \n\nНовите банкови сметки на Еуратек Финанс АД в ОББ АД са :\n\n \n\nIBAN    BG12 UBBS 8155 1016 5664 16 – в лева\n\nIBAN    BG97 UBBS 8155 1416 5664 05 – в евро\n\n \n\nСтарите банкови сметки ще са валидни за входящи плащания  29.11.2024г.\n\n \n\nПоздрави,\n\n \n\n \n\nМихаела Янева, Отдел Счетоводство \nЕуратек Финанс АД, ул.Хан Кубрат 27, 1220  гр.София, България\nT +359 2 813 700,  вътр.117\n\nМоб.тел. +359 886 473 895\n\nm.yaneva@skoda-auto.bg <mailto:m.yaneva@skoda-auto.bg> \n\n \n\n \n\n \n\n\n\n\n\n\n\n\n\nПоздрави,\n\n\n\n\n\n\n\n\nМихаела Янева, Отдел Счетоводство \nЕуратек Финанс АД, ул.Хан Кубрат 27, 1220 гр.София, България\nT +359 2 813 700, вътр.117\nМоб.тел. +359 886 473 895\nm.yaneva@skoda-auto.bg","subject":"Еуратек Финанс АД - ФАКТУРА 03_1000173944","date":"2024-09-12T14:47:24.000Z","to":[{"address":"tbl_ood@mail.bg","name":""},{"address":"tbl_ood@abv.bg","name":""}],"attachmentsData":["Получатель: Тибиел ЕООД\nДоставчик: Еуратек Финанс АД\nАдрес на управление:\nАдрес на управление:\nПерник, пл.Св.Иван Рилски 1\nСофия, ул.Брегалница 113 , ап.9\nИд. № по ЗДДС:\nBG106588084\nИд. № по ЗДДС:\nBG131521276\nЕИК/ЕГН:\n106588084\nЕИК/ЕГН:\n131521276\nОбект:\n02001\nФАКТУРА №: 1000173944\nОРИГИНАЛ\nДата:\n09.09.2024\nНачин на плащане:\nПлащане по банка\nДата на данъчно събитие:\n09.09.2024\nСрок за плащане:\n07.09.2024\nРед Наименование на стоките или услугите\nЕд. цена\nК-во\nСтойност\nлв.\nлв.\n1\nГлавница по Вноска No. 47/03_DL_005818\n374,70\n374.70\n2\nЛизингова лихва по Вноска No. 47/03_DL_005818\n1\n24,06\n24,06\nСума :\n398,76\nВсичко:\n398,76\nЧл.46 ал. 1 т. 1 от ЗДДС\nСума неначисление:\n24.06\nДанъчна основа: 374,70\nДДС ставка: 20\nДДС сума:\n74,92\nСума за плащане:\n473,68\nСловом: Четиристотин седамдесет и три лв. и 68 ст.\nМясто на сделката: София\nФактурата получил: Димитър Йорданов Иванов\nСъставил: Михаела Стефанова Янева\nПодпис :...\nПодпис :.\nДокументьт в без печат, на основание чл.7, ал. 1 от Закона за счетоводство.\nБанка: Обединена Българска Банка\nЕуратек Финанс АД\nBIC: UBBSBGSF\nград: София\nЛева IBAN: BG12 UBBS 8155 1016 5664 16\nтел .: 02 813 700\nEUR IBAN: BG97 UBB$ 8155 1416 5664 05\nфакс: 02 936 26 37\nПолучатель: Тибиел ЕООД\nДоставчик: Еуратек Финанс АД\nАдрес на управление:\nАдрес на управление:\nПерник, пл.Св.Иван Рилски 1\nСофия, ул.Брегалница 113 , ап.9\nИд. № по ЗДДС:\nBG106588084\nИд. № по ЗДДС:\nBG131521276\nЕИК/ЕГН:\n106588084\nЕИК/ЕГН:\n131521276\nОбект:\n02001\nФАКТУРА №: 1000173944\nКОПИЕ\nДата:\n09.09.2024\nНачин на плащане:\nПлащане по банка\nДата на данъчно събитие:\n09.09.2024\nСрок за плащане:\n07.09.2024\nРед Наименование на стоките или услугите\nЕд. цена\nК-во\nСтойност\nлв.\nлв.\n1\nГлавница по Вноска No. 47/03_DL_005818\n374,70\n374.70\n2\nЛизингова лихва по Вноска No. 47/03_DL_005818\n1\n24,06\n24,06\nСума:\n398,76\nВсичко:\n398,76\nЧл.46 ал. 1 т. 1 от ЗДДС\nСума неначисление:\n24.06\nДанъчна основа: 374,70\nДДС ставка: 20\nДДС сума:\n74,92\nСума за плащане:\n473,68\nСловом: Четиристотин седамдесет и три лв. и 68 ст.\nМясто на сделката: София\nФактурата получил: Димитър Йорданов Иванов\nСъставил: Михаела Стефанова Янева\nПодпис :...\nПодпис :.\nДокументьт в без печат, на основание чл.7, ал. 1 от Закона за счетоводство.\nБанка: Обединена Българска Банка\nЕуратек Финанс АД\nBIC: UBBSBGSF\nград: София\nЛева IBAN: BG12 UBBS 8155 1016 5664 16\nтел .: 02 813 700\nEUR IBAN: BG97 UBB$ 8155 1416 5664 05\nфакс: 02 936 26 37"]}