{"attachments":["RSE_2022_V1-part-1.zip","image001.png"],"text":"Уважаема госпожо Гълъбова,\n\n \n\nЗа правилното отнасяне на потребителите по икономически дейности, приложено Ви изпращам актуален Регистър на статистическите единици (РСЕ) – част 1, които да ползвате по  време на работа с Отчет „Доставки на природен газ“ за 2023 година.\n\n \n\nПоздрави,\n\n \n\n \n\nТаня Феодорова\n\nСтарши експерт в отдел \"Статистически изследвания - Перник\"\n\nТериториално статистическо бюро - Югозапад\n\nНационален статистически институт\n\n2300 Перник, ул. Отец Паисий 2\n\nТел.: 00 359 76 6886 64\n\nМоб.тел.: +359 898 590 819\n\nИмейл: tfeodorova@nsi.bg <mailto:tfeodorova@nsi.bg> \n\nwww.nsi.bg <http://www.nsi.bg/>","subject":"Файлове с Регистър на статистическите единици за Отчет \"Доставки на природен газ - 2023 година\" - част 1","date":"2024-05-14T14:54:49.000Z","to":[{"address":"tbl_ood@abv.bg","name":""},{"address":"tbl_ood@mail.bg","name":""}],"attachmentsData":[false,""]}