{"attachments":["Месечен_Акт_01_25_ТИБИЕЛ.pdf","Приложение_1_0040000822_04_02_2025.pdf","ТИБИЕЛ_ЕООД_0040000822_04_02_2025.pdf"],"text":"Уважаеми дами и господа,\n\nВъв връзка със сключен договор за достъп и съхранение на природен газ, приложено Ви изпращаме фактури и приложенията към тях.\n\nМоля за потвърждение за получаване.\n\n\nДенка Асенова\nСчетоводител\nОтдел \"Счетоводство\"\nДирекция \"Финанси и контрол\"\n\"Булгартрансгаз\" ЕАД\n\ne-mail:denka.asenova@bulgartransgaz.bg <mailto:denka.asenova@bulgartransgaz.bg> \nТел: +359 2 939 6187\nwww.bulgartransgaz.bg <http://www.bulgartransgaz.bg> \n________________________________\n\n\nThis email may contain confidential and/or legally privileged information. It is intended exclusively for the addressee(s). \nAs our company operates in accordance with the requirements of GDPR we perceive any disclosure, copying, distribution or any other action with this information as strictly prohibited. In case this message has been sent to you by mistake, please inform us so we can ensure this does not occur anymore and then delete the message and the attachments there to from your system. \nIn case of any inquiries related to GDPR compliance or data protection, please contact our Data Protection Officer at the following email address: dlzd@bulgartransgaz.bg. \nThank you for your cooperation!” \n\n________________________________\n\nТози имейл може да съдържа поверителна и/или юридически привилегирована информация. Тя е предназначена изключително за адресата/ите.\nТъй като нашето Дружество осъществява дейността си в съответствие с изискванията на GDPR възприемаме всяко разкриване, копиране, разпространение и всяко друго действие с тази информация, като строго забранено. В случай, че това съобщение е изпратено до Вас по грешка, моля уведомете ни, за да гарантираме, че това няма да се случва повече и след това изтрийте съобщението и прикачената информация от вашата система.\nЗа всякакви запитвания, свързани със спазването на изискванията на GDPR или защитата на данните, винаги можете да се свържете с нашето длъжностно лице по защита на данните на следния имейл адрес: dlzd@bulgartransgaz.bg.\nБлагодаря Ви за съдействието!\"","subject":"Издадени фактури Булгартрансгаз ЕАД - ТИБИЕЛ ЕООД","date":"2025-02-04T14:52:19.000Z","to":[{"address":"backoffice@tibiel.com","name":""},{"address":"a.ivanova@tibiel.com","name":""},{"address":"tbl_ood@mail.bg","name":""},{"address":"tbl_ood@abv.bg","name":""}],"attachmentsData":["Приложение № 4\nКЪм Договор за съхранение № 6604/15.03.2024 г. на ТИБИЕЛ ЕООД\nМЕСЕЧЕН АКТ\nза месец Януари 2025 г.\nза разпределен капацитет за добив и нагнетаване \"за Ден напред\", \"в рамките на деня\" и добити/нагнетени/съхранени количества природен газ по Договор № 6604/15.03.2024 г. на ТИБИЕЛ ЕООД\nСъхранени количества в ПГХ\nРазпределен капацитет за добив/нагнетаване\n\"ACH Hanpen\" kWh/d\nРазпределен капацитет за добив/нагнетяване\n[kwh]\n\"в рамките на деня\" kWh/d\nПотврдени\nРазпределени\nДата\nколичества за добив\nколичества за\nКоличества съхранени в ПГХ в\n(към 7:00ч.)\n[kwh]\nAO6MB\nначалото на периода:\n\"ден напред\"\n\"ден напред\" прекъоваем\n\"ден напред\"\n\"в рамките на деня\"\n\"в рамките на деня\"\n[kwh]\n[kwh]\nрежим\nnpektcnaem peloIM\nфиз. добив\nрежим вирт. добив\nвирт. нагнетяване\nрежим физ. добив\nрежим вирт.\n354 741 723\nнагнетяване\nH.1\nK.2\nH.4\n.9\n01.01.2025 [\n5 347 319\n349 394 404\n02.01.2025 r\n5 347 319\n5 347 319\n5 347 319\n344 047 085\n0\n03.01.2025 [.\nD\n04.01.2025 r.\n5.347,319\n5 347 319\n338 699 766\n5.347.319\n5 347 319\n333 352 447\n05.01.2025 r.\n5 347 319\n5 347 319\n328 005 128\n06.01.2025 r.\n5 347 319\n5 347 319\n322 657 809\n10\n0\n0\n07.01.2025 r\n5 347 319\n5 347 319\n317 310 490\n08.01.2025 r.\n5 347 319\n5 347 319\n311 963 171\n09.01.2025 r\n5 347 319\n5 347 319\n5 347 319\n306 615 852\nD\n0\n100\n10.01.2025 r\n5 347 319\n301 268 533\n0\n11.01.2025 r\n5 347 319\n5 347 319\n295 921 214\n0\n12.01.2025 г.\n5 347 319\n5 347 319\n290 573 895\n13.01.2025 r.\n5 347 319\n5 347 319\n285 225 576\n0\n0\n14.01.2025 г\n5 347 319\n5 347 319\n279 879 257\n00\n0\n15.01.2025 г.\n5 547 319\n5 547 319\n274 331 938\n0\n16.01.2025 г.\n5 347 319\n5 347.319\n268 984 619\n0\n0\n17.01.2025 r.\n5 347 319\n5 347 319\n263 637 300\n0\n18.01.2025 r\n5 247 319\n5 247 319\n258 369 981\n19.01.2025 г.\n6 347 319\n5 347 319\n253 042 662\n0\n0\n20.01.2025 r.\n5 347 319\n5 347 319\n247 695 343\n0\n0\n0\n0\n00\n21.01.2025 r\n6347 319\n5 347 319\n242 348 024\n0\n0\n22.01.2025 r.\n5 347 319\n5 347 319\n237 000 705\n0\n0\n0\n23.01.2025 г.\n5 347 319\n5 347 319\n231 653 386\n0\n0\n000\n24.01.2025 г.\n5 347.319\n5 347 319\n226 306 067\n0\n221 158 748\n0\n00\n25.01.2025 г.\n5 147 319\n5 147 319\n0\n0\n26.01.2025 r.\n5 147 319\n216 011 429\n0\n0\n00\n27.01.2025 r\n5 147 319\n5 147 319\n5 147 319\n210 864 110\n0\n0\n28.01.2025 r\n5 147 319\n5 147 319\n205 716 791\n0\n0\n0000\n29.01.2025 r.\n4 947 319\n4 947 319\n200 769 472\n00\n30.01.7025 r.\n5 147 319\n5 147 319\n195 622 153\n31.01.2025 f.\n5 147 319\n190 474 834\nlas\n5 147 319\nale\nO6wo 3a Meccya\n164 266 889\n164 266 889\n190 474 834\nAara: 04.02.2025\nЗа \"БУЛГАРТРАНСГАЗ\" ЕАД\nАнтон Георгиев\n2\n/nodnuc/","Приложение 1 към фактура No: 0040000822/04.2.2025 г. по договор 6604/15.03.2024 г.\nКлиент: Тибиел ЕООД\nЕИК: 58X-TIBIEL-LTD-K\nНомер на фактурата 0040000822\nПериод на фактурата: 01.2.2025/28.02.2025\nПредоставена услуга за достъп\nмярка\nколичество\nцена\nстойност\nгодишен интегриран капацитетен продукт - план за\n(лв. без ДДС)\nдействие при изванредни ситуации\nбр.\n94\n1 302.4431\n122 429.65\nмесечен твърд продукт за добив\nMWh/A/M\n720.000\n13.5100\n9 727.20\nОбщо за фактура\nбр\n132 156.85","ФАКТУРА\nNº 0040000822 / 04.02.2025\nОРИГИНАЛ\nПОЛУЧАТЕЛ:\nДОСТАВЧИК:\nТИБИЕЛ ЕООД\nБУЛГАРТРАНСГАЗ ЕАД\nАдрес: гр. Перник. п.к. 2300, ул. Кракра №70\nАдрес: СОФИЯ, БУЛ. ПАНЧО ВЛАДИГЕРОВ 66\nИдентификационен номер: 175203478\nИдентификационен номер: 106588084\nИН по ЗДДС: BG175203478\nИН по ЗДДС: BG106588084\nIBAN: BG20BPB179401065238401 BGN\nДата на възникване на данъчното\nБанка: ЮРОБАНК БЪЛГАРИЯ АД\nBIC: BPBIBGSF\nсъбитие: 04.02.2025\nIBAN: BG54STSA93000027341090 EUR\nДоговор: 6604 / 15.03.2024\nБанка: Банка ДСК\nBIC: STSABGSF\nСедалище и адрес на управление:\nСОФИЯ, БУЛ. ПАНЧО ВЛАДИГЕРОВ 66\n№ Шифър\nНаименование на стоката / услугата\nМарка Количество\nЕд.цена без ДДС Стойност в лева\n1 111300 Годишен интегриран капацитетен продукт - план за\nбр.\n94.000\n1302.443\n122429.65\nдействие при изванредни ситуации\n2 113500 Месечен твърд продукт за добив\nmwhd\n720.000\n13.510\n9727.20\nПериод на фактурата: 01.2.2025/28.02.2025\nПриложение № 1 е неразделна част от Ф-ра № 0040000822 / 04.02.2025\nСловом: сто петдесет и осем хиляди петстотин осемдесет\nи осем ле и 22 ст.\nНачин на плащане:\nСтойност на сделката в лева:\n132 156.85\nПо сметка\nДанъчна основа в лева:\n132 156.85\nПредставител на получателя, МОЛ(име, фамилия)\nДата на падеж:\nДДС в лева 20.00 %\n26 431.37\nДесето число на\nСума за плащане в лева:\n158 588.22\nΛ.Κ. Νο:\nПълном. И/от:\nмесеца\nПродуктова такса в лева:\n0.00\nИздадена на/от: /\nСтоката/услугата получена на:\nСъставил име: Денка Асенова\nПолучатель подпис:\nИдентификационен шифър: 9999\nСъставил подпис:\nОтпечатано от АЖУРФ \"Бонев Софт Одитинг\" ООД www.bsoft.bg. Всички права запазени\nINVOICE\nNº 0040000822 / 04.02.2025\nORIGINAL\nRECEIVER:\nSUPPLIER:\nТИБИЕЛ ЕООД\nBULGARTRANSGAZ EAD\nAddress: гр. Перник. п.к. 2300, ул. Кракра №70\nAddress: Sofia,66, Pancho Vladigerov Blvd\nIndentification Number: 175203478\nIndentification Number: 106588084\nVAT ID: BG175203478\nVAT ID: BG106588084\nIBAN:\nBG20BPBI79401065238401 BGN\nDate of occurrence of the tax event:\n04.02.2025\nBank:\nEUROBANK BULGARIA AD\nBIC: BPBIBGSF\nContract: 6604 / 15.03.2024\nIBAN:\nBG54STSA93000027341090 EUR\nBank:\nDSK\nBIC: STSABGSF\nSeat and registered address:\nSofia,66, Pancho Vladigerov Blvd\nNº\nCode\nName of the good / service\nUnit\nQuantity\nUnit price\nwithout VAT\nValue (in BGN)\n1 111300 Yearly integrated capacity product - emergency plan\nnbr\n94.000\n1302.443\n122429.65\n2 113500 Monthly firm product for withdrawal\nmwhd\n720.000\n13.510\n9727.20\nPeriod of invoice: 01.2.2025/28.02.2025\nAnnex 1 is an integral part of Invoice No. 0040000822 / 04.02.2025\nIn words: BGN one hundred and fifty eight thousand, five\nhundred and eighty eight BGN and 0.22\nMethod of payment:\nTransaction value, in BGN:\n132 156.85\nIn words: EUR eighty one thousand, eighty four EUR and 0.87\nBank transfer\nTax base in BGN:\n132 156.85\nDate of payment:\nVAT in BGN 20.00 %\n26 431.37\nRepresentative of the recipient, financially liable person\nTenth day of the\nAmount to be paid in BGN:\n158 588.22\nmonth\nAmount to be paid in EUR:\n81 084.87\nID card No .:\nPower of Attorney No .:\nProduct charge in BGN:\n0.00\nIssued on / by: /: /\nPrepared by:\nDenka Asenova\nGoods / service received on:\nIndentification code: 9999\nSignature recipient:\nSignature of the person prepared the invoice:\nPrinted by Ajur®\n\"Bonev Soft Auditing\" Ltd www.bsoft.bg All rights reserved"]}